diffai_python-0.4.1.dist-info/METADATA
diffai_python-0.4.1.dist-info/WHEEL
diffai_python/__init__.py
diffai_python/diffai_python.cpython-311-darwin.so
diffai_python-0.4.1.dist-info/RECORD
